apache_arrow_practice/__init__.py
apache_arrow_practice-0.1.0.dist-info/WHEEL
apache_arrow_practice-0.1.0.dist-info/METADATA
apache_arrow_practice-0.1.0.dist-info/RECORD
